LICENCE.txt
README.md
setup.py
modelos_simulacaoestoque/__init__.py
modelos_simulacaoestoque/simulacaoestoque.py
modelos_simulacaoestoque.egg-info/PKG-INFO
modelos_simulacaoestoque.egg-info/SOURCES.txt
modelos_simulacaoestoque.egg-info/dependency_links.txt
modelos_simulacaoestoque.egg-info/top_level.txt