Metadata-Version: 2.1
Name: modelos_simulacaoestoque
Version: 0.6.0
Summary: Modelos de Simulacao para Aula
Home-page: https://github.com/desordi1/simulacaoestoque
Author: Gabriel Desordi
Author-email: gabrielpd1@al.insper.edu.br
License: MIT
Project-URL: Código fonte, https://github.com/desordi1/simulacaoestoque
Project-URL: Download, https://github.com/desordi1/simulacaoestoque
Keywords: modelos simulacao
Classifier: Development Status :: 5 - Production/Stable
Classifier: Intended Audience :: Developers
Classifier: License :: OSI Approved :: MIT License
Classifier: Natural Language :: Portuguese (Brazilian)
Classifier: Operating System :: OS Independent
Classifier: Topic :: Software Development :: Internationalization
Classifier: Topic :: Scientific/Engineering :: Physics
License-File: LICENCE.txt
